Metadata-Version: 2.4
Name: image_processing-vanessacaldas
Version: 0.1.2
Summary: Um pacote simples de processamento de imagens.
Home-page: http://github.com/vanessacaldas/image-processing-package
Author: Vanessa de Souza Caldas
Author-email: vanessacaldaszootecnista@gmail.com
Classifier: Programming Language :: Python :: 3
Classifier: License :: OSI Approved :: MIT License
Requires-Python: >=3.6
Requires-Dist: numpy
Requires-Dist: Pillow
Dynamic: author
Dynamic: author-email
Dynamic: classifier
Dynamic: description
Dynamic: description-content-type
Dynamic: home-page
Dynamic: requires-dist
Dynamic: requires-python
Dynamic: summary
